protego.py
Protego-0.2.1.dist-info/LICENSE
Protego-0.2.1.dist-info/METADATA
Protego-0.2.1.dist-info/WHEEL
Protego-0.2.1.dist-info/top_level.txt
Protego-0.2.1.dist-info/RECORD
